lunchmoney_mcp/__init__.py
lunchmoney_mcp/server.py
lunchmoney_mcp-0.1.4.dist-info/licenses/LICENSE
lunchmoney_mcp-0.1.4.dist-info/METADATA
lunchmoney_mcp-0.1.4.dist-info/WHEEL
lunchmoney_mcp-0.1.4.dist-info/entry_points.txt
lunchmoney_mcp-0.1.4.dist-info/top_level.txt
lunchmoney_mcp-0.1.4.dist-info/RECORD
