Metadata-Version: 2.4
Name: lunchmoney-mcp
Version: 0.1.4
Summary: MCP server for Lunch Money API
Author-email: Assistant <assistant@example.com>
License: MIT
Project-URL: Homepage, https://github.com/MatiasL13/lunchmoney-mcp
Project-URL: Documentation, https://github.com/MatiasL13/lunchmoney-mcp#readme
Project-URL: Repository, https://github.com/MatiasL13/lunchmoney-mcp
Project-URL: Issues, https://github.com/MatiasL13/lunchmoney-mcp/issues
Keywords: mcp,lunch-money,personal-finance,api
Classifier: Development Status :: 4 - Beta
Classifier: Intended Audience :: Developers
Classifier: License :: OSI Approved :: MIT License
Classifier: Programming Language :: Python :: 3
Classifier: Programming Language :: Python :: 3.8
Classifier: Programming Language :: Python :: 3.9
Classifier: Programming Language :: Python :: 3.10
Classifier: Programming Language :: Python :: 3.11
Classifier: Programming Language :: Python :: 3.12
Requires-Python: >=3.8
License-File: LICENSE
Requires-Dist: mcp[cli]>=1.0.0
Requires-Dist: httpx>=0.24.0
Requires-Dist: pydantic>=2.0.0
Requires-Dist: python-dotenv>=1.0.0
Provides-Extra: dev
Requires-Dist: pytest>=7.0.0; extra == "dev"
Requires-Dist: black>=23.0.0; extra == "dev"
Requires-Dist: mypy>=1.0.0; extra == "dev"
Requires-Dist: build>=1.0.0; extra == "dev"
Requires-Dist: twine>=4.0.0; extra == "dev"
Dynamic: license-file
